opsdata_magna_test/__init__.py
opsdata_magna_test/core.py
opsdata_magna_test/version.py
opsdata_magna_test-0.1.0.data/data/LICENSE
opsdata_magna_test-0.1.0.dist-info/LICENSE
opsdata_magna_test-0.1.0.dist-info/METADATA
opsdata_magna_test-0.1.0.dist-info/WHEEL
opsdata_magna_test-0.1.0.dist-info/entry_points.txt
opsdata_magna_test-0.1.0.dist-info/top_level.txt
opsdata_magna_test-0.1.0.dist-info/RECORD
