Metadata-Version: 2.1
Name: opsdata-magna-test
Version: 0.1.0
Summary: A toy ObsPlus dataset of the 2020 Salt Lake City earthquake
Home-page: https://www.github.com/d-chambers/opsdata_magna_test
Author: Derrick Chambers
Author-email: djachambeador@gmail.com
License: BSD
Platform: UNKNOWN
Classifier: Development Status :: 2 - Pre-Alpha
Classifier: Intended Audience :: Developers
Classifier: Natural Language :: English
Classifier: Programming Language :: Python :: 3.6
Classifier: Programming Language :: Python :: 3.7
